gramps_webapi/__init__.py
gramps_webapi/__main__.py
gramps_webapi/_version.py
gramps_webapi/app.py
gramps_webapi/celery.py
gramps_webapi/config.py
gramps_webapi/const.py
gramps_webapi/dbloader.py
gramps_webapi/dbmanager.py
gramps_webapi/profiler.py
gramps_webapi/translogger.py
gramps_webapi/types.py
gramps_webapi/undodb.py
gramps_webapi/wsgi.py
gramps_webapi/api/__init__.py
gramps_webapi/api/auth.py
gramps_webapi/api/cache.py
gramps_webapi/api/check.py
gramps_webapi/api/dna.py
gramps_webapi/api/emails.py
gramps_webapi/api/export.py
gramps_webapi/api/file.py
gramps_webapi/api/html.py
gramps_webapi/api/image.py
gramps_webapi/api/media.py
gramps_webapi/api/media_importer.py
gramps_webapi/api/people_families_cache.py
gramps_webapi/api/ratelimiter.py
gramps_webapi/api/report.py
gramps_webapi/api/s3.py
gramps_webapi/api/tasks.py
gramps_webapi/api/telemetry.py
gramps_webapi/api/util.py
gramps_webapi/api/llm/__init__.py
gramps_webapi/api/llm/agent.py
gramps_webapi/api/llm/deps.py
gramps_webapi/api/llm/tools.py
gramps_webapi/api/resources/__init__.py
gramps_webapi/api/resources/base.py
gramps_webapi/api/resources/bookmarks.py
gramps_webapi/api/resources/chat.py
gramps_webapi/api/resources/citations.py
gramps_webapi/api/resources/config.py
gramps_webapi/api/resources/delete.py
gramps_webapi/api/resources/dna.py
gramps_webapi/api/resources/emit.py
gramps_webapi/api/resources/events.py
gramps_webapi/api/resources/export_media.py
gramps_webapi/api/resources/exporters.py
gramps_webapi/api/resources/face_detection.py
gramps_webapi/api/resources/facts.py
gramps_webapi/api/resources/families.py
gramps_webapi/api/resources/file.py
gramps_webapi/api/resources/filters.py
gramps_webapi/api/resources/history.py
gramps_webapi/api/resources/holidays.py
gramps_webapi/api/resources/import_media.py
gramps_webapi/api/resources/importers.py
gramps_webapi/api/resources/living.py
gramps_webapi/api/resources/match.py
gramps_webapi/api/resources/media.py
gramps_webapi/api/resources/metadata.py
gramps_webapi-3.7.1.dist-info/licenses/LICENSE
gramps_webapi-3.7.1.dist-info/METADATA
gramps_webapi-3.7.1.dist-info/WHEEL
gramps_webapi-3.7.1.dist-info/top_level.txt
gramps_webapi-3.7.1.dist-info/RECORD
